{
  "schema_id": "flat_geography_006_lookup",
  "domain": "flat_geography",
  "examples": [
    {
      "english": "What state or province is Sydney in?",
      "target_table": "table_geography_006",
      "sql_where": "City = 'Sydney'",
      "requires_join": false,
      "join_clause": null,
      "latent_variables": {
        "predicate_type": "lookup_proper_noun",
        "columns_referenced": ["table_geography_006.City"],
        "select_column": "State/Province",
        "operators_used": ["="],
        "conjunction_type": "none",
        "has_temporal": false,
        "temporal_type": null,
        "temporal_expression": null,
        "has_negation": false,
        "negation_scope": null,
        "value_types": ["string_literal"],
        "ambiguity_notes": "none",
        "column_reference_type": "direct",
        "value_extraction_type": "verbatim",
        "value_in_question": "Sydney"
      }
    },
    {
      "english": "What country is Istanbul in?",
      "target_table": "table_geography_006",
      "sql_where": "City = 'Istanbul'",
      "requires_join": false,
      "join_clause": null,
      "latent_variables": {
        "predicate_type": "lookup_proper_noun",
        "columns_referenced": ["table_geography_006.City"],
        "select_column": "Country",
        "operators_used": ["="],
        "conjunction_type": "none",
        "has_temporal": false,
        "temporal_type": null,
        "temporal_expression": null,
        "has_negation": false,
        "negation_scope": null,
        "value_types": ["string_literal"],
        "ambiguity_notes": "none",
        "column_reference_type": "direct",
        "value_extraction_type": "verbatim",
        "value_in_question": "Istanbul"
      }
    },
    {
      "english": "What is the population of Chicago?",
      "target_table": "table_geography_006",
      "sql_where": "City = 'Chicago'",
      "requires_join": false,
      "join_clause": null,
      "latent_variables": {
        "predicate_type": "lookup_proper_noun",
        "columns_referenced": ["table_geography_006.City"],
        "select_column": "Population",
        "operators_used": ["="],
        "conjunction_type": "none",
        "has_temporal": false,
        "temporal_type": null,
        "temporal_expression": null,
        "has_negation": false,
        "negation_scope": null,
        "value_types": ["string_literal"],
        "ambiguity_notes": "none",
        "column_reference_type": "direct",
        "value_extraction_type": "verbatim",
        "value_in_question": "Chicago"
      }
    },
    {
      "english": "What is the elevation of La Paz?",
      "target_table": "table_geography_006",
      "sql_where": "City = 'La Paz'",
      "requires_join": false,
      "join_clause": null,
      "latent_variables": {
        "predicate_type": "lookup_proper_noun",
        "columns_referenced": ["table_geography_006.City"],
        "select_column": "Elevation (m)",
        "operators_used": ["="],
        "conjunction_type": "none",
        "has_temporal": false,
        "temporal_type": null,
        "temporal_expression": null,
        "has_negation": false,
        "negation_scope": null,
        "value_types": ["string_literal"],
        "ambiguity_notes": "none",
        "column_reference_type": "direct",
        "value_extraction_type": "verbatim",
        "value_in_question": "La Paz"
      }
    },
    {
      "english": "What time zone is Dubai in?",
      "target_table": "table_geography_006",
      "sql_where": "City = 'Dubai'",
      "requires_join": false,
      "join_clause": null,
      "latent_variables": {
        "predicate_type": "lookup_proper_noun",
        "columns_referenced": ["table_geography_006.City"],
        "select_column": "Time Zone",
        "operators_used": ["="],
        "conjunction_type": "none",
        "has_temporal": false,
        "temporal_type": null,
        "temporal_expression": null,
        "has_negation": false,
        "negation_scope": null,
        "value_types": ["string_literal"],
        "ambiguity_notes": "none",
        "column_reference_type": "direct",
        "value_extraction_type": "verbatim",
        "value_in_question": "Dubai"
      }
    },
    {
      "english": "What cities are in New South Wales?",
      "target_table": "table_geography_006",
      "sql_where": "\"State/Province\" = 'New South Wales'",
      "requires_join": false,
      "join_clause": null,
      "latent_variables": {
        "predicate_type": "lookup_proper_noun",
        "columns_referenced": ["table_geography_006.State/Province"],
        "select_column": "City",
        "operators_used": ["="],
        "conjunction_type": "none",
        "has_temporal": false,
        "temporal_type": null,
        "temporal_expression": null,
        "has_negation": false,
        "negation_scope": null,
        "value_types": ["string_literal"],
        "ambiguity_notes": "none",
        "column_reference_type": "direct",
        "value_extraction_type": "verbatim",
        "value_in_question": "New South Wales"
      }
    },
    {
      "english": "What is the population of cities in Quebec?",
      "target_table": "table_geography_006",
      "sql_where": "\"State/Province\" = 'Quebec'",
      "requires_join": false,
      "join_clause": null,
      "latent_variables": {
        "predicate_type": "lookup_proper_noun",
        "columns_referenced": ["table_geography_006.State/Province"],
        "select_column": "Population",
        "operators_used": ["="],
        "conjunction_type": "none",
        "has_temporal": false,
        "temporal_type": null,
        "temporal_expression": null,
        "has_negation": false,
        "negation_scope": null,
        "value_types": ["string_literal"],
        "ambiguity_notes": "none",
        "column_reference_type": "direct",
        "value_extraction_type": "verbatim",
        "value_in_question": "Quebec"
      }
    },
    {
      "english": "What cities are in France?",
      "target_table": "table_geography_006",
      "sql_where": "Country = 'France'",
      "requires_join": false,
      "join_clause": null,
      "latent_variables": {
        "predicate_type": "lookup_proper_noun",
        "columns_referenced": ["table_geography_006.Country"],
        "select_column": "City",
        "operators_used": ["="],
        "conjunction_type": "none",
        "has_temporal": false,
        "temporal_type": null,
        "temporal_expression": null,
        "has_negation": false,
        "negation_scope": null,
        "value_types": ["string_literal"],
        "ambiguity_notes": "none",
        "column_reference_type": "direct",
        "value_extraction_type": "verbatim",
        "value_in_question": "France"
      }
    },
    {
      "english": "What is the time zone of Turkish cities?",
      "target_table": "table_geography_006",
      "sql_where": "Country = 'Turkey'",
      "requires_join": false,
      "join_clause": null,
      "latent_variables": {
        "predicate_type": "lookup_proper_noun",
        "columns_referenced": ["table_geography_006.Country"],
        "select_column": "Time Zone",
        "operators_used": ["="],
        "conjunction_type": "none",
        "has_temporal": false,
        "temporal_type": null,
        "temporal_expression": null,
        "has_negation": false,
        "negation_scope": null,
        "value_types": ["string_literal"],
        "ambiguity_notes": "none",
        "column_reference_type": "direct",
        "value_extraction_type": "verbatim",
        "value_in_question": "Turkey"
      }
    },
    {
      "english": "What elevations do Indian cities have?",
      "target_table": "table_geography_006",
      "sql_where": "Country = 'India'",
      "requires_join": false,
      "join_clause": null,
      "latent_variables": {
        "predicate_type": "lookup_proper_noun",
        "columns_referenced": ["table_geography_006.Country"],
        "select_column": "Elevation (m)",
        "operators_used": ["="],
        "conjunction_type": "none",
        "has_temporal": false,
        "temporal_type": null,
        "temporal_expression": null,
        "has_negation": false,
        "negation_scope": null,
        "value_types": ["string_literal"],
        "ambiguity_notes": "none",
        "column_reference_type": "direct",
        "value_extraction_type": "verbatim",
        "value_in_question": "India"
      }
    },
    {
      "english": "What city has a population of 3000000?",
      "target_table": "table_geography_006",
      "sql_where": "Population = 3000000",
      "requires_join": false,
      "join_clause": null,
      "latent_variables": {
        "predicate_type": "lookup_number",
        "columns_referenced": ["table_geography_006.Population"],
        "select_column": "City",
        "operators_used": ["="],
        "conjunction_type": "none",
        "has_temporal": false,
        "temporal_type": null,
        "temporal_expression": null,
        "has_negation": false,
        "negation_scope": null,
        "value_types": ["number"],
        "ambiguity_notes": "none",
        "column_reference_type": "direct",
        "value_extraction_type": "verbatim",
        "value_in_question": "3000000"
      }
    },
    {
      "english": "What country has the city with elevation 2350?",
      "target_table": "table_geography_006",
      "sql_where": "\"Elevation (m)\" = 2350",
      "requires_join": false,
      "join_clause": null,
      "latent_variables": {
        "predicate_type": "lookup_number",
        "columns_referenced": ["table_geography_006.Elevation (m)"],
        "select_column": "Country",
        "operators_used": ["="],
        "conjunction_type": "none",
        "has_temporal": false,
        "temporal_type": null,
        "temporal_expression": null,
        "has_negation": false,
        "negation_scope": null,
        "value_types": ["number"],
        "ambiguity_notes": "none",
        "column_reference_type": "direct",
        "value_extraction_type": "verbatim",
        "value_in_question": "2350"
      }
    },
    {
      "english": "What city has a population of 8000000?",
      "target_table": "table_geography_006",
      "sql_where": "Population = 8000000",
      "requires_join": false,
      "join_clause": null,
      "latent_variables": {
        "predicate_type": "lookup_number",
        "columns_referenced": ["table_geography_006.Population"],
        "select_column": "City",
        "operators_used": ["="],
        "conjunction_type": "none",
        "has_temporal": false,
        "temporal_type": null,
        "temporal_expression": null,
        "has_negation": false,
        "negation_scope": null,
        "value_types": ["number"],
        "ambiguity_notes": "none",
        "column_reference_type": "direct",
        "value_extraction_type": "verbatim",
        "value_in_question": "8000000"
      }
    },
    {
      "english": "What time zone is the city at elevation 5 in?",
      "target_table": "table_geography_006",
      "sql_where": "\"Elevation (m)\" = 5",
      "requires_join": false,
      "join_clause": null,
      "latent_variables": {
        "predicate_type": "lookup_number",
        "columns_referenced": ["table_geography_006.Elevation (m)"],
        "select_column": "Time Zone",
        "operators_used": ["="],
        "conjunction_type": "none",
        "has_temporal": false,
        "temporal_type": null,
        "temporal_expression": null,
        "has_negation": false,
        "negation_scope": null,
        "value_types": ["number"],
        "ambiguity_notes": "none",
        "column_reference_type": "direct",
        "value_extraction_type": "verbatim",
        "value_in_question": "5"
      }
    },
    {
      "english": "What city has 15000000 people?",
      "target_table": "table_geography_006",
      "sql_where": "Population = 15000000",
      "requires_join": false,
      "join_clause": null,
      "latent_variables": {
        "predicate_type": "lookup_number",
        "columns_referenced": ["table_geography_006.Population"],
        "select_column": "City",
        "operators_used": ["="],
        "conjunction_type": "none",
        "has_temporal": false,
        "temporal_type": null,
        "temporal_expression": null,
        "has_negation": false,
        "negation_scope": null,
        "value_types": ["number"],
        "ambiguity_notes": "none",
        "column_reference_type": "direct",
        "value_extraction_type": "verbatim",
        "value_in_question": "15000000"
      }
    },
    {
      "english": "What cities in the UK are on GMT?",
      "target_table": "table_geography_006",
      "sql_where": "Country = 'UK' AND \"Time Zone\" = 'GMT'",
      "requires_join": false,
      "join_clause": null,
      "latent_variables": {
        "predicate_type": "lookup_category",
        "columns_referenced": ["table_geography_006.Country", "table_geography_006.Time Zone"],
        "select_column": "City",
        "operators_used": ["=", "="],
        "conjunction_type": "and",
        "has_temporal": false,
        "temporal_type": null,
        "temporal_expression": null,
        "has_negation": false,
        "negation_scope": null,
        "value_types": ["string_literal", "string_literal"],
        "ambiguity_notes": "none",
        "column_reference_type": "direct",
        "value_extraction_type": "verbatim",
        "value_in_question": "UK, GMT"
      }
    },
    {
      "english": "What cities are in the CET time zone?",
      "target_table": "table_geography_006",
      "sql_where": "\"Time Zone\" = 'CET'",
      "requires_join": false,
      "join_clause": null,
      "latent_variables": {
        "predicate_type": "lookup_category",
        "columns_referenced": ["table_geography_006.Time Zone"],
        "select_column": "City",
        "operators_used": ["="],
        "conjunction_type": "none",
        "has_temporal": false,
        "temporal_type": null,
        "temporal_expression": null,
        "has_negation": false,
        "negation_scope": null,
        "value_types": ["string_literal"],
        "ambiguity_notes": "none",
        "column_reference_type": "direct",
        "value_extraction_type": "verbatim",
        "value_in_question": "CET"
      }
    },
    {
      "english": "What countries are on MST?",
      "target_table": "table_geography_006",
      "sql_where": "\"Time Zone\" = 'MST'",
      "requires_join": false,
      "join_clause": null,
      "latent_variables": {
        "predicate_type": "lookup_category",
        "columns_referenced": ["table_geography_006.Time Zone"],
        "select_column": "Country",
        "operators_used": ["="],
        "conjunction_type": "none",
        "has_temporal": false,
        "temporal_type": null,
        "temporal_expression": null,
        "has_negation": false,
        "negation_scope": null,
        "value_types": ["string_literal"],
        "ambiguity_notes": "none",
        "column_reference_type": "direct",
        "value_extraction_type": "verbatim",
        "value_in_question": "MST"
      }
    },
    {
      "english": "What are the elevations of cities in the UTC+8 time zone?",
      "target_table": "table_geography_006",
      "sql_where": "\"Time Zone\" = 'UTC+8'",
      "requires_join": false,
      "join_clause": null,
      "latent_variables": {
        "predicate_type": "lookup_category",
        "columns_referenced": ["table_geography_006.Time Zone"],
        "select_column": "Elevation (m)",
        "operators_used": ["="],
        "conjunction_type": "none",
        "has_temporal": false,
        "temporal_type": null,
        "temporal_expression": null,
        "has_negation": false,
        "negation_scope": null,
        "value_types": ["string_literal"],
        "ambiguity_notes": "none",
        "column_reference_type": "direct",
        "value_extraction_type": "verbatim",
        "value_in_question": "UTC+8"
      }
    },
    {
      "english": "What Japanese cities are in JST?",
      "target_table": "table_geography_006",
      "sql_where": "Country = 'Japan' AND \"Time Zone\" = 'JST'",
      "requires_join": false,
      "join_clause": null,
      "latent_variables": {
        "predicate_type": "lookup_category",
        "columns_referenced": ["table_geography_006.Country", "table_geography_006.Time Zone"],
        "select_column": "City",
        "operators_used": ["=", "="],
        "conjunction_type": "and",
        "has_temporal": false,
        "temporal_type": null,
        "temporal_expression": null,
        "has_negation": false,
        "negation_scope": null,
        "value_types": ["string_literal", "string_literal"],
        "ambiguity_notes": "none",
        "column_reference_type": "direct",
        "value_extraction_type": "verbatim",
        "value_in_question": "Japan, JST"
      }
    },
    {
      "english": "What province is the city of Vancouver in?",
      "target_table": "table_geography_006",
      "sql_where": "City = 'Vancouver'",
      "requires_join": false,
      "join_clause": null,
      "latent_variables": {
        "predicate_type": "reverse_lookup",
        "columns_referenced": ["table_geography_006.City"],
        "select_column": "State/Province",
        "operators_used": ["="],
        "conjunction_type": "none",
        "has_temporal": false,
        "temporal_type": null,
        "temporal_expression": null,
        "has_negation": false,
        "negation_scope": null,
        "value_types": ["string_literal"],
        "ambiguity_notes": "none",
        "column_reference_type": "direct",
        "value_extraction_type": "verbatim",
        "value_in_question": "Vancouver"
      }
    },
    {
      "english": "What is the elevation of Addis Ababa?",
      "target_table": "table_geography_006",
      "sql_where": "City = 'Addis Ababa'",
      "requires_join": false,
      "join_clause": null,
      "latent_variables": {
        "predicate_type": "reverse_lookup",
        "columns_referenced": ["table_geography_006.City"],
        "select_column": "Elevation (m)",
        "operators_used": ["="],
        "conjunction_type": "none",
        "has_temporal": false,
        "temporal_type": null,
        "temporal_expression": null,
        "has_negation": false,
        "negation_scope": null,
        "value_types": ["string_literal"],
        "ambiguity_notes": "none",
        "column_reference_type": "direct",
        "value_extraction_type": "verbatim",
        "value_in_question": "Addis Ababa"
      }
    },
    {
      "english": "What time zone is Cairo in?",
      "target_table": "table_geography_006",
      "sql_where": "City = 'Cairo'",
      "requires_join": false,
      "join_clause": null,
      "latent_variables": {
        "predicate_type": "reverse_lookup",
        "columns_referenced": ["table_geography_006.City"],
        "select_column": "Time Zone",
        "operators_used": ["="],
        "conjunction_type": "none",
        "has_temporal": false,
        "temporal_type": null,
        "temporal_expression": null,
        "has_negation": false,
        "negation_scope": null,
        "value_types": ["string_literal"],
        "ambiguity_notes": "none",
        "column_reference_type": "direct",
        "value_extraction_type": "verbatim",
        "value_in_question": "Cairo"
      }
    },
    {
      "english": "What country hosted the 2016 Olympics?",
      "target_table": "table_geography_006",
      "sql_where": "City = 'Rio de Janeiro'",
      "requires_join": false,
      "join_clause": null,
      "latent_variables": {
        "predicate_type": "year_as_string",
        "columns_referenced": ["table_geography_006.City"],
        "select_column": "Country",
        "operators_used": ["="],
        "conjunction_type": "none",
        "has_temporal": false,
        "temporal_type": null,
        "temporal_expression": null,
        "has_negation": false,
        "negation_scope": null,
        "value_types": ["string_literal"],
        "ambiguity_notes": "year contextual; city used as filter",
        "column_reference_type": "direct",
        "value_extraction_type": "verbatim",
        "value_in_question": "Rio de Janeiro"
      }
    },
    {
      "english": "What time zone is the city that hosted the 2004 Olympics in?",
      "target_table": "table_geography_006",
      "sql_where": "City = 'Athens'",
      "requires_join": false,
      "join_clause": null,
      "latent_variables": {
        "predicate_type": "year_as_string",
        "columns_referenced": ["table_geography_006.City"],
        "select_column": "Time Zone",
        "operators_used": ["="],
        "conjunction_type": "none",
        "has_temporal": false,
        "temporal_type": null,
        "temporal_expression": null,
        "has_negation": false,
        "negation_scope": null,
        "value_types": ["string_literal"],
        "ambiguity_notes": "year contextual; city used as filter",
        "column_reference_type": "direct",
        "value_extraction_type": "verbatim",
        "value_in_question": "Athens"
      }
    }
  ]
}
