[
  {
    "question": "What was the record at the game against the Indians with a loss of Camacho (1-4)?",
    "headers": [
      "Date",
      "Opponent",
      "Score",
      "Loss",
      "Record"
    ],
    "where_column": "Opponent",
    "where_value": "indians",
    "all_conditions": [
      {
        "column": "Opponent",
        "value": "indians"
      },
      {
        "column": "Loss",
        "value": "camacho (1-4)"
      }
    ]
  },
  {
    "question": "Which Little League World Series took place in Parsippany?",
    "headers": [
      "Year",
      "Champion",
      "City",
      "LLWS",
      "Record"
    ],
    "where_column": "City",
    "where_value": "parsippany"
  },
  {
    "question": "What was the theme for the Top 11 week?",
    "headers": [
      "Week",
      "Theme",
      "Artist",
      "Order sung",
      "Status"
    ],
    "where_column": "Week",
    "where_value": "top 11"
  },
  {
    "question": "Which athlete from Brazil has 2.20 O and 2.25 of XXX?",
    "headers": [
      "Athlete",
      "Nationality",
      "2.15",
      "2.20",
      "2.25",
      "Result"
    ],
    "where_column": "2.20",
    "where_value": "o",
    "all_conditions": [
      {
        "column": "2.20",
        "value": "o"
      },
      {
        "column": "2.25",
        "value": "xxx"
      },
      {
        "column": "Nationality",
        "value": "brazil"
      }
    ]
  },
  {
    "question": "Which builder completed before 1890 and launched on 9 june 1888?",
    "headers": [
      "Name",
      "Builder",
      "Laid down",
      "Launched",
      "Completed"
    ],
    "where_column": "Completed",
    "where_value": "1890",
    "all_conditions": [
      {
        "column": "Completed",
        "value": "1890"
      },
      {
        "column": "Launched",
        "value": "9 june 1888"
      }
    ]
  },
  {
    "question": "Which Captain 2 has a Result of final?",
    "headers": [
      "Date",
      "Captain 1",
      "Team 2",
      "Captain 2",
      "Venue",
      "Result"
    ],
    "where_column": "Result",
    "where_value": "final"
  },
  {
    "question": "What all capacities have turbines between 50-60?",
    "headers": [
      "Name",
      "Turbines",
      "Capacity (MW)",
      "Power (MW\u00b7hr/yr)",
      "Location (county)",
      "Year Operational",
      "Status"
    ],
    "where_column": "Turbines",
    "where_value": "50-60"
  },
  {
    "question": "Who was the judge for the state SD?",
    "headers": [
      "Judge",
      "State",
      "Born/Died",
      "Began active service*",
      "Ended active service"
    ],
    "where_column": "State",
    "where_value": "sd"
  },
  {
    "question": "How many dar are in germany?",
    "headers": [
      "N\u00b0",
      "Television service",
      "Country",
      "Language",
      "Content",
      "DAR",
      "HDTV",
      "Package/Option"
    ],
    "where_column": "Country",
    "where_value": "Germany"
  },
  {
    "question": "Name the city of license with resolution of sd 480i and official website of telemundo.com",
    "headers": [
      "Dish",
      "Callsign",
      "Network",
      "Resolution",
      "City of License",
      "Official Website"
    ],
    "where_column": "Resolution",
    "where_value": "sd 480i",
    "all_conditions": [
      {
        "column": "Resolution",
        "value": "sd 480i"
      },
      {
        "column": "Official Website",
        "value": "telemundo.com"
      }
    ]
  },
  {
    "question": "what is x when faisaly is 0-0?",
    "headers": [
      "\u00d7",
      "Faisaly",
      "Wehdat",
      "Ramtha",
      "Ahli",
      "Jazeera",
      "Hussein",
      "Amman",
      "Orthodoxy",
      "Jeel",
      "Ain Karem"
    ],
    "where_column": "Faisaly",
    "where_value": "0-0"
  },
  {
    "question": "In 2010-11, what was the League name?",
    "headers": [
      "Year",
      "League",
      "Reg. Season",
      "Playoffs",
      "Avg. attendance"
    ],
    "where_column": "Year",
    "where_value": "2010-11"
  },
  {
    "question": "what is the rounds when the engine is mercedes fo110m?",
    "headers": [
      "Entrant",
      "Constructor",
      "Chassis",
      "Engine \u2020",
      "Tyre",
      "Driver",
      "Rounds"
    ],
    "where_column": "Engine \u2020",
    "where_value": "mercedes fo110m"
  },
  {
    "question": "Which Skip has a Third of tony angiboust?",
    "headers": [
      "Nation",
      "Skip",
      "Third",
      "Second",
      "Lead"
    ],
    "where_column": "Third",
    "where_value": "tony angiboust"
  },
  {
    "question": "What is Pronunciation Spelled Checked, when Example Spelled Checked is \"tin /t\u026an/ (\"tin\")\"",
    "headers": [
      "Letter",
      "Pronunciation spelled free",
      "Pronunciation spelled checked",
      "Example spelled free",
      "Example spelled checked"
    ],
    "where_column": "Example spelled checked",
    "where_value": "tin /t\u026an/ (\"tin\")"
  },
  {
    "question": "What was the Position of the Player, Britton Johnsen?",
    "headers": [
      "Player",
      "Nationality",
      "Position",
      "Years in Orlando",
      "School/Club Team"
    ],
    "where_column": "Player",
    "where_value": "britton johnsen"
  },
  {
    "question": "Which class corresponds to more than 2 points, wins greater than 0, and a year earlier than 1973?",
    "headers": [
      "Year",
      "Class",
      "Team",
      "Points",
      "Wins"
    ],
    "where_column": "Points",
    "where_value": "2",
    "all_conditions": [
      {
        "column": "Points",
        "value": "2"
      },
      {
        "column": "Year",
        "value": "1973"
      },
      {
        "column": "Wins",
        "value": "0"
      }
    ]
  },
  {
    "question": "The original artist Joan Osborne has what result?",
    "headers": [
      "Episode",
      "Theme",
      "Song choice",
      "Original artist",
      "Order #",
      "Result"
    ],
    "where_column": "Original artist",
    "where_value": "Joan Osborne"
  },
  {
    "question": "What is the enrollment for Ashland University?",
    "headers": [
      "Institution",
      "Location (all in Ohio)",
      "Nickname",
      "Founded",
      "Type",
      "Enrollment",
      "Joined",
      "Left",
      "Current Conference"
    ],
    "where_column": "Location (all in Ohio)",
    "where_value": "Ashland"
  },
  {
    "question": "Which Features have Yes listed under Datacenter?",
    "headers": [
      "Features",
      "Foundation",
      "Standard",
      "Enterprise",
      "Datacenter",
      "Itanium"
    ],
    "where_column": "Datacenter",
    "where_value": "yes"
  },
  {
    "question": "Name the Player who has a Country of united states, and a To par of \u20135?",
    "headers": [
      "Place",
      "Player",
      "Country",
      "Score",
      "To par"
    ],
    "where_column": "Country",
    "where_value": "united states",
    "all_conditions": [
      {
        "column": "Country",
        "value": "united states"
      },
      {
        "column": "To par",
        "value": "\u20135"
      }
    ]
  },
  {
    "question": "Wha is the average number of bronze of hungary, which has less than 1 silver?",
    "headers": [
      "Rank",
      "Nation",
      "Gold",
      "Silver",
      "Bronze",
      "Total"
    ],
    "where_column": "Nation",
    "where_value": "hungary",
    "all_conditions": [
      {
        "column": "Nation",
        "value": "hungary"
      },
      {
        "column": "Silver",
        "value": "1"
      }
    ]
  },
  {
    "question": "How many viewers did the episode directed by David Nutter draw in?",
    "headers": [
      "Series #",
      "Season #",
      "Title",
      "Directed by",
      "Written by",
      "Original air date",
      "Production code",
      "U.S. viewers (million)"
    ],
    "where_column": "Directed by",
    "where_value": "David Nutter"
  },
  {
    "question": "what is the City of license that has a 1,400 watts Power",
    "headers": [
      "City of license",
      "Identifier",
      "Frequency",
      "Power",
      "Class",
      "RECNet"
    ],
    "where_column": "Power",
    "where_value": "1,400 watts"
  },
  {
    "question": "Name the total number of serial number for 24 wd no",
    "headers": [
      "LMS No.",
      "WD No.",
      "Builder",
      "Serial No.",
      "Date built"
    ],
    "where_column": "WD No.",
    "where_value": "24"
  }
]